.gitignore
CHANGES
README
setup.py
monitcall/__init__.py
monitcall/endless.py
monitcall/monitcall.py
monitcall/tests.py
monitcall.egg-info/PKG-INFO
monitcall.egg-info/SOURCES.txt
monitcall.egg-info/dependency_links.txt
monitcall.egg-info/entry_points.txt
monitcall.egg-info/requires.txt
monitcall.egg-info/top_level.txt
monitcall.egg-info/zip-safe