Metadata-Version: 1.0
Name: monitcall
Version: 0.3.1
Summary: Call and monitor executables
Home-page: http://github.com/tomgross/monitcall
Author: Tom Gross
Author-email: itconsense@gmail.com
License: ZPL 2.1
Platform: UNKNOWN
Classifier: Development Status :: 4 - Beta
Classifier: Environment :: Console
Classifier: Intended Audience :: System Administrators
Classifier: License :: OSI Approved :: Zope Public License
Classifier: Programming Language :: Python
Classifier: Topic :: System :: Systems Administration
Classifier: Topic :: Utilities
